datajunction_server/__about__.py
datajunction_server/__init__.py
datajunction_server/alembic.ini
datajunction_server/config.py
datajunction_server/constants.py
datajunction_server/enum.py
datajunction_server/errors.py
datajunction_server/naming.py
datajunction_server/service_clients.py
datajunction_server/superset.py
datajunction_server/transpilation.py
datajunction_server/typing.py
datajunction_server/utils.py
datajunction_server/alembic/README
datajunction_server/alembic/env.py
datajunction_server/alembic/script.py.mako
datajunction_server/alembic/versions/2023_12_20_1829-724445d2b29d_initial_migration.py
datajunction_server/alembic/versions/2024_01_08_2034-945d44abcd32_add_dimension_links.py
datajunction_server/alembic/versions/2024_01_11_2032-c74b11566d82_add_column_order.py
datajunction_server/alembic/versions/2024_01_18_2011-20f060b02772_switch_enum_values.py
datajunction_server/alembic/versions/2024_01_23_0617-c9cef8864ecb_add_missing_table_attribute_to_source_.py
datajunction_server/alembic/versions/2024_01_23_1655-a8e22109be24_availability_state_s_valid_through_ts_.py
datajunction_server/alembic/versions/2024_02_22_0713-d61fb7e48cc3_cascade_deletes_to_dimension_links.py
datajunction_server/alembic/versions/2024_04_30_1556-de7ec1c82fe0_add_query_requests.py
datajunction_server/alembic/versions/2024_05_09_1420-9b1227ff17f4_update_backfill_spec.py
datajunction_server/alembic/versions/2024_05_21_0012-57fc93ef6947_add_query_id_to_queryrequest.py
datajunction_server/alembic/versions/2024_06_21_1301-640a814db2d8_add_collection_tables.py
datajunction_server/alembic/versions/2024_07_12_0348-34171c92dd6d_set_user_username_to_be_unique.py
datajunction_server/alembic/versions/2024_08_18_0036-f3c9b40deb6f_add_create_by_to_nodes_node_revisions_.py
datajunction_server/alembic/versions/2024_10_24_0015-4d6ab789e456_add_a_map_of_links_to_availability_state.py
datajunction_server/alembic/versions/2024_10_26_0340-70904373eab3_add_indexes_on_history_and_node_tables.py
datajunction_server-0.0.56.dist-info/METADATA
datajunction_server-0.0.56.dist-info/WHEEL
datajunction_server-0.0.56.dist-info/entry_points.txt
datajunction_server-0.0.56.dist-info/RECORD
