Metadata-Version: 2.4
Name: datajunction-server
Version: 0.0.56
Summary: DataJunction server library for running to a DataJunction server
Project-URL: Homepage, https://datajunction.io
Project-URL: Repository, https://github.com/DataJunction/dj
License: MIT
Keywords: metrics,semanticlayer
Classifier: License :: OSI Approved :: MIT License
Classifier: Operating System :: OS Independent
Classifier: Programming Language :: Python :: 3.10
Classifier: Programming Language :: Python :: 3.11
Requires-Python: <3.12,>=3.10
Requires-Dist: alembic>=1.10.3
Requires-Dist: antlr4-python3-runtime==4.13.1
Requires-Dist: bcrypt<=4.3.0,>=4.0.1
Requires-Dist: cachelib<1.0.0,>=0.10.2
Requires-Dist: cachetools>=5.3.1
Requires-Dist: celery<6.0.0,>=5.2.7
Requires-Dist: cryptography<=45.0.0
Requires-Dist: fastapi-cache2>=0.2.1
Requires-Dist: fastapi>=0.110.0
Requires-Dist: google-api-python-client>=2.95.0
Requires-Dist: google-auth-httplib2>=0.1.0
Requires-Dist: google-auth-oauthlib>=1.0.0
Requires-Dist: httpx>=0.27.0
Requires-Dist: jinja2>=3.1.4
Requires-Dist: line-profiler>=4.0.3
Requires-Dist: msgpack<2.0.0,>=1.0.5
Requires-Dist: nbformat>=5.10.4
Requires-Dist: opentelemetry-instrumentation-fastapi==0.38b0
Requires-Dist: passlib>=1.7.4
Requires-Dist: psycopg>=3.1.16
Requires-Dist: pydantic-settings>=2.10.1
Requires-Dist: pydantic<2.11,>=2.0
Requires-Dist: pyjwt[crypto]>=2.8.0
Requires-Dist: python-dotenv<1.0.0,>=0.19.0
Requires-Dist: python-jose>=3.3.0
Requires-Dist: python-multipart>=0.0.20
Requires-Dist: pyyaml>=6.0.1
Requires-Dist: redis<5.0.0,>=4.5.4
Requires-Dist: requests<=2.29.0,>=2.28.2
Requires-Dist: rich<14.0.0,>=13.3.3
Requires-Dist: sqlalchemy-utils<1.0.0,>=0.40.0
Requires-Dist: sqlalchemy>=2
Requires-Dist: sse-starlette<=2.0.0,>=1.6.0
Requires-Dist: strawberry-graphql>=0.235.0
Requires-Dist: types-cachetools>=5.3.0.6
Requires-Dist: yamlfix>=1.16.0
Requires-Dist: yarl<2.0.0,>=1.8.2
Provides-Extra: all
Requires-Dist: snowflake-connector-python>=3.0.0; extra == 'all'
Provides-Extra: snowflake
Requires-Dist: snowflake-connector-python>=3.0.0; extra == 'snowflake'
Provides-Extra: transpilation
Requires-Dist: sqlglot>=18.0.1; extra == 'transpilation'
Provides-Extra: uvicorn
Requires-Dist: uvicorn[standard]>=0.21.1; extra == 'uvicorn'
